AUTHORS
LICENSE
MANIFEST.in
README.rst
setup.py
appointments/__init__.py
appointments/admin.py
appointments/forms.py
appointments/models.py
appointments/tasks.py
appointments/views.py
appointments/handlers/__init__.py
appointments/handlers/base.py
appointments/handlers/confirm.py
appointments/handlers/move.py
appointments/handlers/new.py
appointments/handlers/quit.py
appointments/handlers/status.py
appointments/migrations/0001_initial.py
appointments/migrations/__init__.py
appointments/tests/__init__.py
appointments/tests/base.py
appointments/tests/test_app.py
appointments/tests/test_handlers.py
appointments/tests/test_tasks.py
rapidsms_appointments.egg-info/PKG-INFO
rapidsms_appointments.egg-info/SOURCES.txt
rapidsms_appointments.egg-info/dependency_links.txt
rapidsms_appointments.egg-info/not-zip-safe
rapidsms_appointments.egg-info/requires.txt
rapidsms_appointments.egg-info/top_level.txt