Metadata-Version: 1.1
Name: rapidsms-appointments
Version: 0.1.0
Summary: A reusable RapidSMS application for sending appointment reminders.
Home-page: https://github.com/caktus/rapidsms-appointments/
Author: Caktus Consulting Group
Author-email: solutions@caktusgroup.com
License: BSD
Platform: UNKNOWN
Classifier: Topic :: Internet :: WWW/HTTP :: Dynamic Content
Classifier: Intended Audience :: Developers
Classifier: License :: OSI Approved :: BSD License
Classifier: Programming Language :: Python
Classifier: Programming Language :: Python :: 2.6
Classifier: Programming Language :: Python :: 2.7
Classifier: Framework :: Django
Classifier: Development Status :: 4 - Beta
Classifier: Operating System :: OS Independent
